SecuriPy.py
SecuriPy-3.0.2.dist-info/METADATA
SecuriPy-3.0.2.dist-info/WHEEL
SecuriPy-3.0.2.dist-info/top_level.txt
SecuriPy-3.0.2.dist-info/RECORD
