Metadata-Version: 2.1
Name: SecuriPy
Version: 3.0.2
Summary: Encrypter and Decrypter of all types of human-readable file formats and much more Using Python
Home-page: https://pypi.org/project/SecuriPy
Author: Anupam Kanoongo
Author-email: programmer.tiak@gmail.com
License: MIT
Project-URL: Our Website, https://anupam1707.github.io/
Project-URL: Our YT Handle, https://youtube.com/@developer.anupam
Classifier: Programming Language :: Python :: 3
Classifier: License :: OSI Approved :: MIT License
Classifier: Operating System :: OS Independent
Requires-Python: >=3.6
